CHANGES.md
LICENSE.txt
MANIFEST.in
README.md
TODO.md
pyproject.toml
setup.cfg
setup.py
tox.ini
src/pyramid_session_redis/__init__.py
src/pyramid_session_redis/compat.py
src/pyramid_session_redis/connection.py
src/pyramid_session_redis/exceptions.py
src/pyramid_session_redis/py.typed
src/pyramid_session_redis/session.py
src/pyramid_session_redis/util.py
src/pyramid_session_redis.egg-info/PKG-INFO
src/pyramid_session_redis.egg-info/SOURCES.txt
src/pyramid_session_redis.egg-info/dependency_links.txt
src/pyramid_session_redis.egg-info/not-zip-safe
src/pyramid_session_redis.egg-info/requires.txt
src/pyramid_session_redis.egg-info/top_level.txt
src/pyramid_session_redis/docs/.gitignore
src/pyramid_session_redis/docs/Makefile
src/pyramid_session_redis/docs/advanced.rst
src/pyramid_session_redis/docs/api.rst
src/pyramid_session_redis/docs/conf.py
src/pyramid_session_redis/docs/contributing.rst
src/pyramid_session_redis/docs/gettingstarted.rst
src/pyramid_session_redis/docs/index.rst
src/pyramid_session_redis/docs/make.bat
src/pyramid_session_redis/docs/redis.rst
tests/__init__.py
tests/_util.py
tests/test_config.py
tests/test_connection.py
tests/test_factory.py
tests/test_pyramid.py
tests/test_serializers.py
tests/test_session.py
tests/test_support.py
tests/test_util.py
tests/web_app.py