Metadata-Version: 2.4
Name: pyramid_session_redis
Version: 1.8.0
Summary: High performance and actively maintained server-side session framework for Pyramid and Redis.
Home-page: https://github.com/jvanasco/pyramid_session_redis
Author: Jonathan Vanasco
Author-email: jonathan@findmeon.com
License: BSD
Keywords: pyramid session redis
Classifier: Intended Audience :: Developers
Classifier: Framework :: Pyramid
Classifier: Programming Language :: Python :: 3
Classifier: Programming Language :: Python :: 3.7
Classifier: Programming Language :: Python :: 3.8
Classifier: Programming Language :: Python :: 3.9
Classifier: Programming Language :: Python :: 3.10
Classifier: Programming Language :: Python :: 3.11
Classifier: Programming Language :: Python :: 3.12
Classifier: Programming Language :: Python :: 3.13
License-File: LICENSE.txt
Requires-Dist: redis>=4.0.0
Requires-Dist: pyramid>=2
Requires-Dist: zope.interface
Requires-Dist: typing_extensions
Provides-Extra: testing
Requires-Dist: redis>=4.0.0; extra == "testing"
Requires-Dist: pyramid>=2; extra == "testing"
Requires-Dist: zope.interface; extra == "testing"
Requires-Dist: typing_extensions; extra == "testing"
Requires-Dist: mypy; extra == "testing"
Requires-Dist: nose; extra == "testing"
Requires-Dist: pytest; extra == "testing"
Requires-Dist: types-webob; extra == "testing"
Requires-Dist: webob; extra == "testing"
Requires-Dist: webtest; extra == "testing"
Requires-Dist: waitress; extra == "testing"
Requires-Dist: coverage; extra == "testing"
Provides-Extra: docs
Requires-Dist: sphinx; extra == "docs"
Dynamic: author
Dynamic: author-email
Dynamic: classifier
Dynamic: description
Dynamic: description-content-type
Dynamic: home-page
Dynamic: keywords
Dynamic: license
Dynamic: license-file
Dynamic: provides-extra
Dynamic: requires-dist
Dynamic: summary
